google/cloud/bigquery/__init__.py
google/cloud/bigquery/_helpers.py
google/cloud/bigquery/_http.py
google/cloud/bigquery/_job_helpers.py
google/cloud/bigquery/_pandas_helpers.py
google/cloud/bigquery/_pyarrow_helpers.py
google/cloud/bigquery/_tqdm_helpers.py
google/cloud/bigquery/_versions_helpers.py
google/cloud/bigquery/client.py
google/cloud/bigquery/dataset.py
google/cloud/bigquery/encryption_configuration.py
google/cloud/bigquery/enums.py
google/cloud/bigquery/exceptions.py
google/cloud/bigquery/external_config.py
google/cloud/bigquery/format_options.py
google/cloud/bigquery/iam.py
google/cloud/bigquery/model.py
google/cloud/bigquery/opentelemetry_tracing.py
google/cloud/bigquery/py.typed
google/cloud/bigquery/query.py
google/cloud/bigquery/retry.py
google/cloud/bigquery/schema.py
google/cloud/bigquery/standard_sql.py
google/cloud/bigquery/table.py
google/cloud/bigquery/version.py
google/cloud/bigquery/dbapi/__init__.py
google/cloud/bigquery/dbapi/_helpers.py
google/cloud/bigquery/dbapi/connection.py
google/cloud/bigquery/dbapi/cursor.py
google/cloud/bigquery/dbapi/exceptions.py
google/cloud/bigquery/dbapi/types.py
google/cloud/bigquery/job/__init__.py
google/cloud/bigquery/job/base.py
google/cloud/bigquery/job/copy_.py
google/cloud/bigquery/job/extract.py
google/cloud/bigquery/job/load.py
google/cloud/bigquery/job/query.py
google/cloud/bigquery/magics/__init__.py
google/cloud/bigquery/magics/magics.py
google/cloud/bigquery/magics/line_arg_parser/__init__.py
google/cloud/bigquery/magics/line_arg_parser/exceptions.py
google/cloud/bigquery/magics/line_arg_parser/lexer.py
google/cloud/bigquery/magics/line_arg_parser/parser.py
google/cloud/bigquery/magics/line_arg_parser/visitors.py
google/cloud/bigquery/routine/__init__.py
google/cloud/bigquery/routine/routine.py
google/cloud/bigquery_v2/__init__.py
google/cloud/bigquery_v2/types/__init__.py
google/cloud/bigquery_v2/types/encryption_config.py
google/cloud/bigquery_v2/types/model.py
google_cloud_bigquery-3.34.0.dist-info/LICENSE
google_cloud_bigquery-3.34.0.dist-info/METADATA
google_cloud_bigquery-3.34.0.dist-info/WHEEL
google_cloud_bigquery-3.34.0.dist-info/top_level.txt
google_cloud_bigquery-3.34.0.dist-info/RECORD
