Metadata-Version: 2.1
Name: google-cloud-bigquery
Version: 3.34.0
Summary: Google BigQuery API client library
Author-email: Google LLC <googleapis-packages@google.com>
License: Apache 2.0
Project-URL: Repository, https://github.com/googleapis/python-bigquery
Classifier: Development Status :: 5 - Production/Stable
Classifier: Intended Audience :: Developers
Classifier: License :: OSI Approved :: Apache Software License
Classifier: Programming Language :: Python
Classifier: Programming Language :: Python :: 3
Classifier: Programming Language :: Python :: 3.9
Classifier: Programming Language :: Python :: 3.10
Classifier: Programming Language :: Python :: 3.11
Classifier: Programming Language :: Python :: 3.12
Classifier: Programming Language :: Python :: 3.13
Classifier: Operating System :: OS Independent
Classifier: Topic :: Internet
Requires-Python: >=3.9
License-File: LICENSE
Requires-Dist: google-api-core[grpc]<3.0.0,>=2.11.1
Requires-Dist: google-auth<3.0.0,>=2.14.1
Requires-Dist: google-cloud-core<3.0.0,>=2.4.1
Requires-Dist: google-resumable-media<3.0.0,>=2.0.0
Requires-Dist: packaging>=24.2.0
Requires-Dist: python-dateutil<3.0.0,>=2.8.2
Requires-Dist: requests<3.0.0,>=2.21.0
Provides-Extra: bqstorage
Requires-Dist: google-cloud-bigquery-storage<3.0.0,>=2.18.0; extra == "bqstorage"
Requires-Dist: grpcio<2.0.0,>=1.47.0; extra == "bqstorage"
Requires-Dist: grpcio<2.0.0,>=1.49.1; python_version >= "3.11" and extra == "bqstorage"
Requires-Dist: pyarrow>=4.0.0; extra == "bqstorage"
Provides-Extra: pandas
Requires-Dist: pandas>=1.3.0; extra == "pandas"
Requires-Dist: pandas-gbq>=0.26.1; extra == "pandas"
Requires-Dist: grpcio<2.0.0,>=1.47.0; extra == "pandas"
Requires-Dist: grpcio<2.0.0,>=1.49.1; python_version >= "3.11" and extra == "pandas"
Requires-Dist: pyarrow>=3.0.0; extra == "pandas"
Requires-Dist: db-dtypes<2.0.0,>=1.0.4; extra == "pandas"
Provides-Extra: ipywidgets
Requires-Dist: ipywidgets>=7.7.1; extra == "ipywidgets"
Requires-Dist: ipykernel>=6.2.0; extra == "ipywidgets"
Provides-Extra: geopandas
Requires-Dist: geopandas<2.0.0,>=0.9.0; extra == "geopandas"
Requires-Dist: Shapely<3.0.0,>=1.8.4; extra == "geopandas"
Provides-Extra: ipython
Requires-Dist: ipython>=7.23.1; extra == "ipython"
Requires-Dist: bigquery-magics>=0.6.0; extra == "ipython"
Provides-Extra: matplotlib
Requires-Dist: matplotlib<=3.9.2,>=3.7.1; python_version == "3.9" and extra == "matplotlib"
Requires-Dist: matplotlib>=3.10.3; python_version >= "3.10" and extra == "matplotlib"
Provides-Extra: tqdm
Requires-Dist: tqdm<5.0.0,>=4.23.4; extra == "tqdm"
Provides-Extra: opentelemetry
Requires-Dist: opentelemetry-api>=1.1.0; extra == "opentelemetry"
Requires-Dist: opentelemetry-sdk>=1.1.0; extra == "opentelemetry"
Requires-Dist: opentelemetry-instrumentation>=0.20b0; extra == "opentelemetry"
Provides-Extra: bigquery-v2
Requires-Dist: proto-plus<2.0.0,>=1.22.3; extra == "bigquery-v2"
Requires-Dist: protobuf!=4.21.0,!=4.21.1,!=4.21.2,!=4.21.3,!=4.21.4,!=4.21.5,<7.0.0,>=3.20.2; extra == "bigquery-v2"
Provides-Extra: all
Requires-Dist: google-cloud-bigquery[bigquery_v2,bqstorage,geopandas,ipython,ipywidgets,matplotlib,opentelemetry,pandas,tqdm]; extra == "all"
